conversimple/__init__.py
conversimple/agent.py
conversimple/callbacks.py
conversimple/connection.py
conversimple/tools.py
conversimple/utils.py
conversimple-0.2.0.dist-info/METADATA
conversimple-0.2.0.dist-info/WHEEL
conversimple-0.2.0.dist-info/entry_points.txt
conversimple-0.2.0.dist-info/top_level.txt
conversimple-0.2.0.dist-info/RECORD
