Metadata-Version: 2.4
Name: conversimple
Version: 0.2.0
Summary: Python SDK for Conversimple Conversational AI Platform
Home-page: https://github.com/conversimple/conversimple-sdk
Author: Conversimple
Author-email: support@conversimple.com
Project-URL: Bug Tracker, https://github.com/conversimple/conversimple-sdk/issues
Project-URL: Documentation, https://docs.conversimple.com/sdk
Project-URL: Platform, https://platform.conversimple.com
Keywords: conversational ai,voice ai,chatbot,websocket,sdk,speech to text,text to speech
Classifier: Development Status :: 3 - Alpha
Classifier: Intended Audience :: Developers
Classifier: Topic :: Software Development :: Libraries :: Python Modules
Classifier: Topic :: Communications :: Chat
Classifier: Topic :: Internet :: WWW/HTTP :: Dynamic Content
Classifier: License :: OSI Approved :: MIT License
Classifier: Programming Language :: Python :: 3
Classifier: Programming Language :: Python :: 3.8
Classifier: Programming Language :: Python :: 3.9
Classifier: Programming Language :: Python :: 3.10
Classifier: Programming Language :: Python :: 3.11
Classifier: Programming Language :: Python :: 3.12
Requires-Python: >=3.8
Requires-Dist: websockets>=12.0
Requires-Dist: aiofiles>=23.0
Requires-Dist: aiohttp>=3.8.0
Provides-Extra: dev
Requires-Dist: pytest>=7.0; extra == "dev"
Requires-Dist: pytest-asyncio>=0.21.0; extra == "dev"
Requires-Dist: black>=23.0; extra == "dev"
Requires-Dist: flake8>=6.0; extra == "dev"
Requires-Dist: mypy>=1.0; extra == "dev"
Provides-Extra: examples
Requires-Dist: aiofiles>=23.0; extra == "examples"
Requires-Dist: aiohttp>=3.8.0; extra == "examples"
Dynamic: author
Dynamic: author-email
Dynamic: classifier
Dynamic: description
Dynamic: description-content-type
Dynamic: home-page
Dynamic: keywords
Dynamic: project-url
Dynamic: provides-extra
Dynamic: requires-dist
Dynamic: requires-python
Dynamic: summary
